easyentry/__init__.py
easyentry-0.0.9.dist-info/WHEEL
easyentry-0.0.9.dist-info/DESCRIPTION.rst
easyentry-0.0.9.dist-info/top_level.txt
easyentry-0.0.9.dist-info/METADATA
easyentry-0.0.9.dist-info/RECORD
easyentry-0.0.9.dist-info/metadata.json
